{"categories":{"list":[{"anchor":true,"cardinality":"bijective","id":"sailor","kind":"nominal","label":"Sailor","values":[{"glyph":"","id":"suki","label":"Suki"},{"glyph":"","id":"bjorn","label":"Bjorn"},{"glyph":"","id":"mira","label":"Mira"}]},{"anchor":false,"cardinality":"bijective","id":"boat","kind":"nominal","label":"Boat","values":[{"glyph":"","id":"sloop","label":"Sloop","phrase":"skippered the sloop","refPhrase":"sloop skipper"},{"glyph":"","id":"cutter","label":"Cutter","phrase":"skippered the cutter","refPhrase":"cutter skipper"},{"glyph":"","id":"ketch","label":"Ketch","phrase":"skippered the ketch","refPhrase":"ketch skipper"}]}],"n":2},"constraints":[{"clueText":"Mira skippered the cutter.","id":"c1","operands":[{"cat":"sailor","value":"mira"},{"cat":"boat","value":"cutter"}],"params":{},"renderHint":"eq","type":"eq"},{"clueText":"Suki skippered the sloop.","id":"c2","operands":[{"cat":"sailor","value":"suki"},{"cat":"boat","value":"sloop"}],"params":{},"renderHint":"eq","type":"eq"}],"entities":["e0","e1","e2"],"hintTrace":[{"forces":{"cat":"boat","entity":"e0","value":"sloop"},"fromClues":["c2"]},{"forces":{"cat":"boat","entity":"e2","value":"cutter"},"fromClues":["c1"]},{"forces":{"cat":"boat","entity":"e1","value":"ketch"},"fromClues":["c1"]}],"puzzleId":"2026-07-02","scenarioId":"harbor-regatta","schemaVersion":2,"shapeId":"grid","solution":{"e0":{"boat":"sloop","sailor":"suki"},"e1":{"boat":"ketch","sailor":"bjorn"},"e2":{"boat":"cutter","sailor":"mira"}},"story":"A light breeze is up over the bay for the summer regatta, and three sailors have drawn their boats up on the shingle while Captain Reyes, who has run the race for years, sorts out the results from a soggy notebook after the wash from a passing ferry. Each sailor has a different boat. Using the clues, match every sailor to their boat.","subjectNoun":"sailor","templateRev":1,"tier":"easy","variant":1}
