{"categories":{"list":[{"anchor":true,"cardinality":"bijective","id":"watchmaker","kind":"nominal","label":"Watchmaker","values":[{"glyph":"","id":"bruno","label":"Bruno"},{"glyph":"","id":"celeste","label":"Celeste"},{"glyph":"","id":"yusuf","label":"Yusuf"},{"glyph":"","id":"ida","label":"Ida"},{"glyph":"","id":"marcel","label":"Marcel"}]},{"anchor":false,"cardinality":"bijective","glyphPack":"color","id":"cloth","kind":"nominal","label":"Cloth","values":[{"glyph":"color.orange","id":"orange","label":"Orange cloth","phrase":"used the orange cloth","refPhrase":"orange-cloth watchmaker"},{"glyph":"color.blue","id":"blue","label":"Blue cloth","phrase":"used the blue cloth","refPhrase":"blue-cloth watchmaker"},{"glyph":"color.purple","id":"purple","label":"Purple cloth","phrase":"used the purple cloth","refPhrase":"purple-cloth watchmaker"},{"glyph":"color.green","id":"green","label":"Green cloth","phrase":"used the green cloth","refPhrase":"green-cloth watchmaker"},{"glyph":"color.yellow","id":"yellow","label":"Yellow cloth","phrase":"used the yellow cloth","refPhrase":"yellow-cloth watchmaker"}]},{"anchor":false,"cardinality":"bijective","id":"repair","kind":"numeric","label":"Repair","unit":"repairs","values":[{"glyph":"","id":"repair7","label":"7 repairs","magnitude":7,"phrase":"completed 7 repairs"},{"glyph":"","id":"repair6","label":"6 repairs","magnitude":6,"phrase":"completed 6 repairs"},{"glyph":"","id":"repair4","label":"4 repairs","magnitude":4,"phrase":"completed 4 repairs"},{"glyph":"","id":"repair3","label":"3 repairs","magnitude":3,"phrase":"completed 3 repairs"},{"glyph":"","id":"repair2","label":"2 repairs","magnitude":2,"phrase":"completed 2 repairs"}]},{"anchor":false,"cardinality":"bijective","id":"timepiece","kind":"nominal","label":"Timepiece","values":[{"glyph":"","id":"mantelclock","label":"Mantel clock","phrase":"serviced the mantel clock","refPhrase":"mantel-clock hand"},{"glyph":"","id":"wristwatch","label":"Wristwatch","phrase":"serviced the wristwatch","refPhrase":"wristwatch hand"},{"glyph":"","id":"pocketwatch","label":"Pocket watch","phrase":"serviced the pocket watch","refPhrase":"pocket-watch hand"},{"glyph":"","id":"carriageclock","label":"Carriage clock","phrase":"serviced the carriage clock","refPhrase":"carriage-clock hand"},{"glyph":"","id":"cuckooclock","label":"Cuckoo clock","phrase":"serviced the cuckoo clock","refPhrase":"cuckoo-clock hand"}]}],"n":4},"constraints":[{"clueText":"It was Yusuf who completed 6 repairs.","id":"c1","operands":[{"cat":"watchmaker","value":"yusuf"},{"cat":"repair","value":"repair6"}],"params":{},"renderHint":"eq","type":"eq"},{"clueText":"The one who serviced the carriage clock was not the blue-cloth watchmaker.","id":"c2","operands":[{"cat":"cloth","value":"blue"},{"cat":"timepiece","value":"carriageclock"}],"params":{},"renderHint":"neq","type":"neq"},{"clueText":"the yellow-cloth watchmaker completed 6 repairs.","id":"c3","operands":[{"cat":"cloth","value":"yellow"},{"cat":"repair","value":"repair6"}],"params":{},"renderHint":"eq","type":"eq"},{"clueText":"It was the purple-cloth watchmaker who serviced the pocket watch.","id":"c4","operands":[{"cat":"cloth","value":"purple"},{"cat":"timepiece","value":"pocketwatch"}],"params":{},"renderHint":"eq","type":"eq"},{"clueText":"Yusuf was not the one who serviced the mantel clock.","id":"c5","operands":[{"cat":"watchmaker","value":"yusuf"},{"cat":"timepiece","value":"mantelclock"}],"params":{},"renderHint":"neq","type":"neq"},{"clueText":"Celeste completed 2 repairs.","id":"c6","operands":[{"cat":"watchmaker","value":"celeste"},{"cat":"repair","value":"repair2"}],"params":{},"renderHint":"eq","type":"eq"},{"clueText":"The one who serviced the mantel clock was not 4 repairs.","id":"c7","operands":[{"cat":"repair","value":"repair4"},{"cat":"timepiece","value":"mantelclock"}],"params":{},"renderHint":"neq","type":"neq"},{"clueText":"Of Bruno and Celeste, one serviced the carriage clock and the other serviced the pocket watch.","id":"c8","operands":[{"cat":"watchmaker","value":"bruno"},{"cat":"watchmaker","value":"celeste"},{"cat":"timepiece","value":"carriageclock"},{"cat":"timepiece","value":"pocketwatch"}],"params":{},"renderHint":"oneEachOf","type":"oneEachOf"},{"clueText":"Of Celeste and Ida, one serviced the pocket watch and the other serviced the wristwatch.","id":"c9","operands":[{"cat":"watchmaker","value":"celeste"},{"cat":"watchmaker","value":"ida"},{"cat":"timepiece","value":"pocketwatch"},{"cat":"timepiece","value":"wristwatch"}],"params":{},"renderHint":"oneEachOf","type":"oneEachOf"},{"clueText":"It was Marcel who used the orange cloth.","id":"c10","operands":[{"cat":"watchmaker","value":"marcel"},{"cat":"cloth","value":"orange"}],"params":{},"renderHint":"eq","type":"eq"},{"clueText":"Ida completed 1 more repairs than Celeste.","id":"c11","operands":[{"cat":"watchmaker","value":"ida"},{"cat":"watchmaker","value":"celeste"}],"params":{"delta":1,"dir":"greater","numericCat":"repair"},"renderHint":"numDiff","type":"numDiff"}],"entities":["e0","e1","e2","e3","e4"],"hintTrace":[{"forces":{"cat":"cloth","entity":"e4","value":"orange"},"fromClues":["c10"]},{"forces":{"cat":"cloth","entity":"e3","value":"blue"},"fromClues":["c2"]},{"forces":{"cat":"cloth","entity":"e1","value":"purple"},"fromClues":["c4"]},{"forces":{"cat":"cloth","entity":"e0","value":"green"},"fromClues":["c1"]},{"forces":{"cat":"cloth","entity":"e2","value":"yellow"},"fromClues":["c3"]},{"forces":{"cat":"repair","entity":"e4","value":"repair7"},"fromClues":["c1"]},{"forces":{"cat":"repair","entity":"e2","value":"repair6"},"fromClues":["c1","c3"]},{"forces":{"cat":"repair","entity":"e0","value":"repair4"},"fromClues":["c7"]},{"forces":{"cat":"repair","entity":"e3","value":"repair3"},"fromClues":["c1"]},{"forces":{"cat":"repair","entity":"e1","value":"repair2"},"fromClues":["c6"]},{"forces":{"cat":"timepiece","entity":"e4","value":"mantelclock"},"fromClues":["c5","c7"]},{"forces":{"cat":"timepiece","entity":"e3","value":"wristwatch"},"fromClues":["c9"]},{"forces":{"cat":"timepiece","entity":"e1","value":"pocketwatch"},"fromClues":["c4","c8","c9"]},{"forces":{"cat":"timepiece","entity":"e0","value":"carriageclock"},"fromClues":["c2","c8"]},{"forces":{"cat":"timepiece","entity":"e2","value":"cuckooclock"},"fromClues":["c1"]}],"puzzleId":"2026-06-27","scenarioId":"watchmaker-bench","schemaVersion":2,"shapeId":"grid","solution":{"e0":{"cloth":"green","repair":"repair4","timepiece":"carriageclock","watchmaker":"bruno"},"e1":{"cloth":"purple","repair":"repair2","timepiece":"pocketwatch","watchmaker":"celeste"},"e2":{"cloth":"yellow","repair":"repair6","timepiece":"cuckooclock","watchmaker":"yusuf"},"e3":{"cloth":"blue","repair":"repair3","timepiece":"wristwatch","watchmaker":"ida"},"e4":{"cloth":"orange","repair":"repair7","timepiece":"mantelclock","watchmaker":"marcel"}},"story":"Brass shavings glint under the lamp as five watchmakers bend over the bench, and old Esposito pieces together whose morning was whose after a toppled parts tray sent the job tickets fluttering, every grandfather clock still ticking out of step. Each watchmaker has a different cloth, repair and timepiece. Using the clues, match every watchmaker to their cloth, repair and timepiece.","subjectNoun":"watchmaker","templateRev":1,"tier":"sharp","variant":1}
