{"categories":{"list":[{"anchor":true,"cardinality":"bijective","id":"director","kind":"nominal","label":"Director","values":[{"glyph":"","id":"noor","label":"Noor"},{"glyph":"","id":"cleo","label":"Cleo"},{"glyph":"","id":"dev","label":"Dev"},{"glyph":"","id":"rafael","label":"Rafael"}]},{"anchor":false,"cardinality":"bijective","id":"genre","kind":"nominal","label":"Genre","values":[{"glyph":"","id":"comedy","label":"Comedy","phrase":"screened the comedy","refPhrase":"comedy director"},{"glyph":"","id":"fantasy","label":"Fantasy","phrase":"screened the fantasy","refPhrase":"fantasy director"},{"glyph":"","id":"western","label":"Western","phrase":"screened the western","refPhrase":"western director"},{"glyph":"","id":"thriller","label":"Thriller","phrase":"screened the thriller","refPhrase":"thriller director"}]},{"anchor":false,"cardinality":"bijective","id":"slot","kind":"numeric","label":"Slot","values":[{"glyph":"","id":"slot6","label":"Slot 6","magnitude":6,"phrase":"screened in slot 6"},{"glyph":"","id":"slot1","label":"Slot 1","magnitude":1,"phrase":"screened in slot 1"},{"glyph":"","id":"slot3","label":"Slot 3","magnitude":3,"phrase":"screened in slot 3"},{"glyph":"","id":"slot4","label":"Slot 4","magnitude":4,"phrase":"screened in slot 4"}]}],"n":3},"constraints":[{"clueText":"Dev was 3 further down the running order than Noor.","id":"c1","operands":[{"cat":"director","value":"dev"},{"cat":"director","value":"noor"}],"params":{"delta":3,"dir":"greater","numericCat":"slot"},"renderHint":"numDiff","type":"numDiff"},{"clueText":"It was Fantasy who screened in slot 4.","id":"c2","operands":[{"cat":"genre","value":"fantasy"},{"cat":"slot","value":"slot4"}],"params":{},"renderHint":"eq","type":"eq"},{"clueText":"Comedy was not the one who screened in slot 1.","id":"c3","operands":[{"cat":"genre","value":"comedy"},{"cat":"slot","value":"slot1"}],"params":{},"renderHint":"neq","type":"neq"},{"clueText":"Rafael was not the one who screened in slot 4.","id":"c4","operands":[{"cat":"director","value":"rafael"},{"cat":"slot","value":"slot4"}],"params":{},"renderHint":"neq","type":"neq"},{"clueText":"The one who screened the thriller was Dev.","id":"c5","operands":[{"cat":"director","value":"dev"},{"cat":"genre","value":"thriller"}],"params":{},"renderHint":"eq","type":"eq"}],"entities":["e0","e1","e2","e3"],"hintTrace":[{"forces":{"cat":"genre","entity":"e0","value":"comedy"},"fromClues":["c3"]},{"forces":{"cat":"genre","entity":"e1","value":"fantasy"},"fromClues":["c2"]},{"forces":{"cat":"genre","entity":"e3","value":"western"},"fromClues":["c1"]},{"forces":{"cat":"genre","entity":"e2","value":"thriller"},"fromClues":["c5"]},{"forces":{"cat":"slot","entity":"e2","value":"slot6"},"fromClues":["c1"]},{"forces":{"cat":"slot","entity":"e3","value":"slot1"},"fromClues":["c3"]},{"forces":{"cat":"slot","entity":"e0","value":"slot3"},"fromClues":["c1"]},{"forces":{"cat":"slot","entity":"e1","value":"slot4"},"fromClues":["c2","c4"]}],"puzzleId":"2026-06-25","scenarioId":"film-festival","schemaVersion":2,"shapeId":"grid","solution":{"e0":{"director":"noor","genre":"comedy","slot":"slot3"},"e1":{"director":"cleo","genre":"fantasy","slot":"slot4"},"e2":{"director":"dev","genre":"thriller","slot":"slot6"},"e3":{"director":"rafael","genre":"western","slot":"slot1"}},"story":"The little riverside film festival is winding into its final evening, and four directors are gathered in the lobby while the festival curator, who programmes the whole event, tries to reconstruct the running order after the sudden power cut shuffled the printed cards. Each director has a different genre and slot. Using the clues, match every director to their genre and slot.","subjectNoun":"director","templateRev":1,"tier":"standard","variant":1}
